[
    {
        "category_id": 1,
        "title": "Mens new style Winter Casual Outwear Jackets 2022 Arika",
        "url": "https://i.ibb.co/jD3Grtp/image.png"
    },
    {
        "category_id": 2,
        "title": "Men's Slim Fit Casual One-Button Suit Coat Jacket Formal Business Blazers",
        "url": "https://i.ibb.co/7V33p8c/image.png"
    },
    {
        "category_id": 3,
        "title": "Stylish Denim Jeans Pant For Men",
        "url": "https://i.ibb.co/RP4VgcV/image.png"
    },
    {
        "category_id": 4,
        "title": "Stylish Long Sleeve Casual Shirt For Man - Shirt For Men - Shirt",
        "url": "https://i.ibb.co/ZXWzZDR/image.png"
    },
    {
        "category_id": 5,
        "title": "Maroon Jacquard Fashion Design Front-Open Sweater for Women",
        "url": "https://i.ibb.co/3vDjgKV/image.png"
    }
]